pgarrow.py
pgarrow-0.0.9.dist-info/METADATA
pgarrow-0.0.9.dist-info/WHEEL
pgarrow-0.0.9.dist-info/entry_points.txt
pgarrow-0.0.9.dist-info/licenses/LICENSE
pgarrow-0.0.9.dist-info/RECORD
