Metadata-Version: 2.4
Name: pgarrow
Version: 0.0.9
Summary: A SQLAlchemy PostgreSQL dialect for ADBC (Arrow Database Connectivity)
Project-URL: Source, https://github.com/michalc/pgarrow
Author-email: Michal Charemza <michal@charemza.name>
License-File: LICENSE
Classifier: License :: OSI Approved :: MIT License
Classifier: Programming Language :: Python :: 3
Classifier: Topic :: Database
Requires-Python: >=3.10.0
Requires-Dist: adbc-driver-postgresql>=1.9.0
Requires-Dist: pyarrow>=15.0.0; python_version < '3.13'
Requires-Dist: pyarrow>=18.0.0; python_version >= '3.13'
Requires-Dist: sqlalchemy>=2.0.41; python_version >= '3.13'
Requires-Dist: sqlalchemy>=2.0.7; python_version < '3.13'
Provides-Extra: ci
Requires-Dist: adbc-driver-postgresql==1.9.0; extra == 'ci'
Requires-Dist: pytest; extra == 'ci'
Requires-Dist: pytest-cov; extra == 'ci'
Requires-Dist: sqlalchemy==2.0.41; (python_version >= '3.13') and extra == 'ci'
Requires-Dist: sqlalchemy==2.0.7; (python_version < '3.13') and extra == 'ci'
Provides-Extra: ci-pyarrow-15-0-0
Requires-Dist: pyarrow==15.0.0; extra == 'ci-pyarrow-15-0-0'
Provides-Extra: ci-pyarrow-16-0-0
Requires-Dist: pyarrow==16.0.0; extra == 'ci-pyarrow-16-0-0'
Provides-Extra: ci-pyarrow-17-0-0
Requires-Dist: pyarrow==17.0.0; extra == 'ci-pyarrow-17-0-0'
Provides-Extra: ci-pyarrow-18-0-0
Requires-Dist: pyarrow==18.0.0; extra == 'ci-pyarrow-18-0-0'
Provides-Extra: ci-pyarrow-19-0-0
Requires-Dist: pyarrow==19.0.0; extra == 'ci-pyarrow-19-0-0'
Provides-Extra: ci-pyarrow-20-0-0
Requires-Dist: pyarrow==20.0.0; extra == 'ci-pyarrow-20-0-0'
Provides-Extra: ci-sqlalchemy-1
Requires-Dist: sqlalchemy==1.4.24; extra == 'ci-sqlalchemy-1'
Provides-Extra: dev
Requires-Dist: pytest-cov; extra == 'dev'
Requires-Dist: pytest>=7.2.1; extra == 'dev'
